ebrow/README.md
ebrow/edb/__init__.py
ebrow/edb/afDummy.py
ebrow/edb/afFreezeDetect.py
ebrow/edb/afHasHead.py
ebrow/edb/aslplot.py
ebrow/edb/bargraph.py
ebrow/edb/basegraph.py
ebrow/edb/bg_rmob.py
ebrow/edb/datasource.py
ebrow/edb/dateintervaldialog.py
ebrow/edb/distplot.py
ebrow/edb/ebrow_rc.py
ebrow/edb/heatmap.py
ebrow/edb/hm_rmob.py
ebrow/edb/logprint.py
ebrow/edb/main.py
ebrow/edb/mainwindow.py
ebrow/edb/mapplot.py
ebrow/edb/mapplot3d.py
ebrow/edb/miplot.py
ebrow/edb/pandasmodel.py
ebrow/edb/powerplot.py
ebrow/edb/prefs.py
ebrow/edb/reports.py
ebrow/edb/rtsconfig.py
ebrow/edb/screenshots.py
ebrow/edb/settings.py
ebrow/edb/splash.py
ebrow/edb/statplot.py
ebrow/edb/stats.py
ebrow/edb/thumbnails_browser.py
ebrow/edb/ui_afdummy.py
ebrow/edb/ui_affreezedetect.py
ebrow/edb/ui_afhashead.py
ebrow/edb/ui_dateintervaldialog.py
ebrow/edb/ui_mainwindow.py
ebrow/edb/utilities.py
ebrow/edb/assets/css/reset.css
ebrow/edb/assets/css/rmob.css
ebrow/edb/assets/css/style.css
ebrow/edb/assets/css/table.css
ebrow/edb/assets/img/Logo GABB.jpeg
ebrow/edb/assets/img/calendar.png
ebrow/edb/assets/img/data.png
ebrow/edb/assets/img/events.png
ebrow/edb/assets/img/graph.png
ebrow/edb/assets/img/index.png
ebrow/edb/assets/img/logo.png
ebrow/edb/assets/img/radio.png
ebrow/edb/assets/img/site.png
ebrow/edb/resources/colormaps/cividis.png
ebrow/edb/resources/colormaps/colorgramme.png
ebrow/edb/resources/colormaps/echoes.png
ebrow/edb/resources/colormaps/gray.png
ebrow/edb/resources/colormaps/inferno.png
ebrow/edb/resources/colormaps/magma.png
ebrow/edb/resources/colormaps/plasma.png
ebrow/edb/resources/colormaps/viridis.png
ebrow/edb/resources/icons/LICENSES
ebrow/edb/resources/icons/application-pdf.png
ebrow/edb/resources/icons/application-vnd.ms-excel.png
ebrow/edb/resources/icons/applications-office-5.png
ebrow/edb/resources/icons/atlantik-2.png
ebrow/edb/resources/icons/cmap2D.png
ebrow/edb/resources/icons/cmap3D.png
ebrow/edb/resources/icons/configure-4.png
ebrow-0.6.dist-info/licenses/LICENSE.txt
ebrow-0.6.dist-info/METADATA
ebrow-0.6.dist-info/WHEEL
ebrow-0.6.dist-info/entry_points.txt
ebrow-0.6.dist-info/top_level.txt
ebrow-0.6.dist-info/RECORD
