Metadata-Version: 2.4
Name: ebrow
Version: 0.6
Summary: Echoes Data Browser (Ebrow) is a data navigation and report generation tool for Echoes.
Home-page: https://www.gabb.it/echoes/
Author: Bertani Giuseppe Massimo
Author-email: Giuseppe Massimo Bertani <gm_bertani@yahoo.it>
License:                     GNU GENERAL PUBLIC LICENSE
Project-URL: Homepage, http://www.gabb.it/echoes/
Project-URL: Echoes SF page, https://sourceforge.net/projects/echoes/
Project-URL: Echoes FB page, https://www.facebook.com/gmbertani
Keywords: meteor,echoes,SDR,GABB,RMOB
Classifier: Development Status :: 3 - Alpha
Classifier: Intended Audience :: End Users/Desktop
Classifier: Intended Audience :: Education
Classifier: Intended Audience :: Science/Research
Classifier: Topic :: Software Development :: Build Tools
Classifier: License :: OSI Approved :: GNU General Public License v3 or later (GPLv3+)
Classifier: Programming Language :: Python :: 3
Requires-Python: >=3.10
License-File: LICENSE.txt
Requires-Dist: matplotlib>=3.7.1
Requires-Dist: numpy>=1.24.3
Requires-Dist: pandas>=2.0.0
Requires-Dist: PyQt5>=5.15.7
Requires-Dist: setuptools>=61.0
Requires-Dist: mplcursors>=0.5.2
Requires-Dist: python-dateutil>=2.8.2
Requires-Dist: pyqtspinner>=2.0.0
Requires-Dist: openpyxl>=3.1.2
Requires-Dist: jinja2>=3.1.2
Requires-Dist: scipy>=1.11
Requires-Dist: scikit-image>=0.2.2
Requires-Dist: psutil==6.0.0
Requires-Dist: opencv-python-headless==4.11.0.86
Requires-Dist: astropy==6.1.7
Dynamic: author
Dynamic: home-page
Dynamic: license-file
